dm_client/__init__.py
dm_client/spatial/__init__.py
dm_client/spatial/apps.py
dm_client/spatial/exceptions.py
dm_client/spatial/managers.py
dm_client/spatial/models.py
dm_client/spatial/service.py
dm_client/spatial/migrations/0001_initial.py
dm_client/spatial/migrations/__init__.py
dm_client/spatial/tests/__init__.py
dm_client_spatial-1.0.1.dist-info/licenses/LICENSE
dm_client_spatial-1.0.1.dist-info/METADATA
dm_client_spatial-1.0.1.dist-info/WHEEL
dm_client_spatial-1.0.1.dist-info/top_level.txt
dm_client_spatial-1.0.1.dist-info/RECORD
